ppmi_downloader/__init__.py
ppmi_downloader/guessed_to_real.json
ppmi_downloader/ppmi_downloader.py
ppmi_downloader/ppmi_logger.py
ppmi_downloader/ppmi_navigator.py
ppmi_downloader/selenium_grid_utils.py
ppmi_downloader/study_data_to_checkbox_id.json
ppmi_downloader/utils.py
ppmi_downloader/tests/test_ppmi_downloader.py
ppmi_downloader-0.7.6.dist-info/METADATA
ppmi_downloader-0.7.6.dist-info/WHEEL
ppmi_downloader-0.7.6.dist-info/entry_points.txt
ppmi_downloader-0.7.6.dist-info/licenses/LICENSE
ppmi_downloader-0.7.6.dist-info/RECORD
