Metadata-Version: 2.3
Name: ppmi_downloader
Version: 0.7.6
Summary: A downloader of PPMI files.
Project-URL: Bug Tracker, https://github.com/LivingPark-MRI/ppmi-scraper/issues
Author-email: Tristan Glatard <tristan.glatard@concordia.ca>
License: MIT License
Classifier: License :: OSI Approved :: MIT License
Classifier: Programming Language :: Python :: 3
Requires-Python: >=3.10
Requires-Dist: beautifulsoup4
Requires-Dist: icecream
Requires-Dist: lxml
Requires-Dist: pandas
Requires-Dist: pathspec
Requires-Dist: selenium
Requires-Dist: spython
Requires-Dist: tqdm
Requires-Dist: webdriver-manager>=4.0.0
